arvan_dns.py
arvan_dns-1.0.7.dist-info/METADATA
arvan_dns-1.0.7.dist-info/WHEEL
arvan_dns-1.0.7.dist-info/entry_points.txt
arvan_dns-1.0.7.dist-info/top_level.txt
arvan_dns-1.0.7.dist-info/RECORD
