Metadata-Version: 2.1
Name: arvan-dns
Version: 1.0.7
Summary: Arvan DNS updater
Home-page: https://github.com/seyed-dev/arvan-dns
Author: SeYeD.DeV
Author-email: me@seyed.dev
License: UNKNOWN
Platform: UNKNOWN
Requires-Dist: requests
Requires-Dist: argparse
